SmartDriveML/MainCode.py
SmartDriveML/__init__.py
SmartDriveML/mlFunctions.py
SmartDriveML/priceAnalysis.py
SmartDriveML-0.0.12.dist-info/METADATA
SmartDriveML-0.0.12.dist-info/WHEEL
SmartDriveML-0.0.12.dist-info/top_level.txt
SmartDriveML-0.0.12.dist-info/RECORD
