Metadata-Version: 2.1
Name: SmartDriveML
Version: 0.0.12
Summary: SmartDriveML: Driving Industrial Projects with Affordable ML Solutions, Frameworks and Cloud Choices
Home-page: UNKNOWN
Author: Hrishikesh Thakurdesai
Author-email: hrishikesh.thakurdesai.92@gmail.com
License: UNKNOWN
Keywords: python,machine learning,pyspark,cloud
Platform: UNKNOWN
Classifier: Development Status :: 1 - Planning 
Classifier: Intended Audience :: Developers
Classifier: Programming Language :: Python :: 3
Classifier: Operating System :: Unix
Classifier: Operating System :: MacOS :: MacOS X
Classifier: Operating System :: Microsoft :: Windows
Requires-Dist: pandas
